Metadata-Version: 1.0
Name: fixwhitespace
Version: 0.1
Summary: Fix whitespace in files
Home-page: https://github.com/honzo0481/fixwhitespace
Author: honzo0481
Author-email: gonzalesre@gmail.com
License: MIT
Platform: UNKNOWN
